amulet_nbt/__init__.py
amulet_nbt/_array.cpython-310-darwin.so
amulet_nbt/_array.pyi
amulet_nbt/_compound.cpython-310-darwin.so
amulet_nbt/_compound.pyi
amulet_nbt/_const.cpython-310-darwin.so
amulet_nbt/_dtype.py
amulet_nbt/_errors.cpython-310-darwin.so
amulet_nbt/_float.cpython-310-darwin.so
amulet_nbt/_float.pyi
amulet_nbt/_int.cpython-310-darwin.so
amulet_nbt/_int.pyi
amulet_nbt/_list.cpython-310-darwin.so
amulet_nbt/_list.pyi
amulet_nbt/_load_nbt.cpython-310-darwin.so
amulet_nbt/_load_nbt.pyi
amulet_nbt/_load_snbt.cpython-310-darwin.so
amulet_nbt/_load_snbt.pyi
amulet_nbt/_named_tag.cpython-310-darwin.so
amulet_nbt/_named_tag.pyi
amulet_nbt/_numeric.cpython-310-darwin.so
amulet_nbt/_numeric.pyi
amulet_nbt/_string.cpython-310-darwin.so
amulet_nbt/_string.pyi
amulet_nbt/_util.cpython-310-darwin.so
amulet_nbt/_util.pyi
amulet_nbt/_value.cpython-310-darwin.so
amulet_nbt/_value.pyi
amulet_nbt/_version.py
amulet_nbt/py.typed
amulet_nbt/__pyinstaller/__init__.py
amulet_nbt/__pyinstaller/hook-amulet_nbt.py
amulet_nbt-2.1.5.dist-info/licenses/LICENSE
amulet_nbt-2.1.5.dist-info/METADATA
amulet_nbt-2.1.5.dist-info/WHEEL
amulet_nbt-2.1.5.dist-info/entry_points.txt
amulet_nbt-2.1.5.dist-info/top_level.txt
amulet_nbt-2.1.5.dist-info/RECORD
